calculatormp/__init__.py
calculatormp/calculator.py
calculatormp-0.0.5.dist-info/METADATA
calculatormp-0.0.5.dist-info/WHEEL
calculatormp-0.0.5.dist-info/licenses/LICENSE
calculatormp-0.0.5.dist-info/RECORD
