Metadata-Version: 2.3
Name: calculatormp
Version: 0.0.5
Summary: A package containing basic arithmetic operations
Project-URL: Home, https://github.com/pociusmartynas/calculator-py
Author-email: Martynas Pocius <martynaspocyus@gmail.com>
License-File: LICENSE
Classifier: License :: OSI Approved :: MIT License
Classifier: Operating System :: OS Independent
Classifier: Programming Language :: Python :: 3
Requires-Python: >=3.8
